nautobot_aristacv_importer/__init__.py
nautobot_aristacv_importer/cli.py
nautobot_aristacv_importer/config.py
nautobot_aristacv_importer/diffsync/cloudvision.py
nautobot_aristacv_importer/diffsync/cvutils.py
nautobot_aristacv_importer/diffsync/models.py
nautobot_aristacv_importer/diffsync/nautobot.py
nautobot_aristacv_importer/diffsync/nbutils.py
nautobot_aristacv_importer-1.0.0.dev0.dist-info/entry_points.txt
nautobot_aristacv_importer-1.0.0.dev0.dist-info/WHEEL
nautobot_aristacv_importer-1.0.0.dev0.dist-info/METADATA
nautobot_aristacv_importer-1.0.0.dev0.dist-info/RECORD
